ms_recognizers_choice/__init__.py
ms_recognizers_choice/choice/__init__.py
ms_recognizers_choice/choice/constants.py
ms_recognizers_choice/choice/extractors.py
ms_recognizers_choice/choice/models.py
ms_recognizers_choice/choice/parsers.py
ms_recognizers_choice/choice/recognizers_choice.py
ms_recognizers_choice/choice/english/__init__.py
ms_recognizers_choice/choice/english/boolean.py
ms_recognizers_choice/resources/__init__.py
ms_recognizers_choice/resources/english_choice.py
recognizers_choice/__init__.py
recognizers_choice/choice/__init__.py
recognizers_choice/choice/constants.py
recognizers_choice/choice/extractors.py
recognizers_choice/choice/models.py
recognizers_choice/choice/parsers.py
recognizers_choice/choice/recognizers_choice.py
recognizers_choice/choice/english/__init__.py
recognizers_choice/choice/english/boolean.py
recognizers_choice/resources/__init__.py
recognizers_choice/resources/english_choice.py
ms_recognizers_text_choice-1.0.0.1.dist-info/METADATA
ms_recognizers_text_choice-1.0.0.1.dist-info/WHEEL
ms_recognizers_text_choice-1.0.0.1.dist-info/top_level.txt
ms_recognizers_text_choice-1.0.0.1.dist-info/RECORD
